{"A":["A"],
"ADJECTIVE":["American", "Angelic", "Angry", "Atomic", "Baby", "Beautiful", "Big", "Black", "Blue", "Bright", "Broken", "Canadian", "Canine", "Christian", "Cold", "Concrete", "Curvaceous", "Dark", "Dead", "Deadly", "Deep", "Diamond", "Digital", "Dismal", "Divine", "Egyptian", "Eldritch", "Electric", "Embarassing", "Emerald", "Erotic", "Exciting", "Extreme", "Fabulous", "Feline", "Flying", "Frozen", "Future", "German", "Gleaming", "Gliding", "Golden", "Good", "Grateful", "Green", "Grey", "Grotesque", "Heathen", "Heavenly", "High", "Holy", "Hot", "Inner", "International", "Japanese", "Killing", "Large", "Lesbian", "Liquid", "Little", "Lonely", "Loving", "Lupine", "Magical", "Magnificent", "Marvellous", "Melting", "Mortal", "Mysterious", "Mystical", "Noble", "Nuclear", "Opulent", "Orange", "Outer", "Pagan", "Pale", "Paranoid", "Pink", "Poisonous", "Proud", "Psychedelic", "Purple", "Quiet", "Radiant", "Red", "Repellent", "Rolling", "Ruby", "Russian", "Screaming", "Shapely", "Silent", "Silver", "Small", "Smoking", "Soaring", "Spiritual", "Splendid", "Steely", "Stupid", "Sumptuous", "Sympathetic", "Teenage", "Theoretical", "Throbbing", "Tidal", "Trusting", "Unholy", "Vast", "Velvet", "Warm", "White", "Wild", "Yellow"],
"ADVERBS":["Gently", "Patiently", "Quickly", "Slowly", "Violently", "Absurdly", "Cruelly", "Silently", "Loudly", "Falsely", "Truly", "Really", "Oddly", "Weirdly", "Strangely", "Rapidly", "Coldly", "Warmly"],
"AFTERTYPE":["'n Roll", "Core", "Core", "Core", "Fusion", "Hybrid", "Metal", "In Opposition", "Techno", "Wave", "Without Adjectives"],
"AMOUNT":["Half", "Quarter", "One Third", "Two Thirds", "Three Quarters", "All"],
"BEING":["We Are", "She is", "I am", "We Have", "They Are", "He is", "She isn't", "He isn't", "They Aren't", "They Have", "She has", "He has"],
"BEINGPRESENT":["We Are", "She is", "I am", "You Are", "They Are", "He is", "She Isn't", "He Isn't", "They Aren't", "They Were"],
"COLLECTIVE":["Aces", "Aliens", "Alliance", "Angels", "Apes", "Astronauts", "Barbarians", "Bards", "Boys", "Brigade", "Brothers", "Butterflies", "Children", "Collective", "Company", "Concubines", "Corporation", "Cosmonauts", "Crows", "Dancers", "Department", "Destroyers", "Division", "Eaters", "Explorers", "Family", "Fathers", "Force", "Lieutenants", "Gang", "Girls", "Hooligans", "Intruders", "Jokers", "Kings", "Knights", "Lesbians", "Lunatics", "Mechanics", "Men", "Ministry", "Mothers", "Orphans", "Patrol", "Pilots", "Police", "Queens", "Ravens", "Rioters", "Savages", "Set", "Sisters", "Soldiers", "Sorceresses", "Sorcerors", "Squad", "Squadron", "Terrorists", "Vampires", "Warlords", "Warriors", "Witches", "Wizards", "Women", "Zombies"],
"COREGENRE":["Ambient", "Blues", "Breakbeat", "Calypso", "Country", "Dance", "Danger", "Disco", "Doo-wop", "Downtempo", "Drone", "Dub", "Electro", "Emo", "Folk", "Funk", "Garage", "Gospel", "Hardcore", "Hop", "House", "Industrial", "Jazz", "Merengue", "Metal", "Noise", "Outsider", "Pop", "Psychedelia", "Punk", "Raga", "Rap", "Reggae", "Rock", "Rockabilly", "Soul", "Swing", "Techno", "Trance"],
"CURRENTVERB":["Die", "Explode", "Exist", "Resist", "Persist", "Desist", "Live", "Collapse", "Fly", "Run"],
"FIRSTNAME":["Alice", "Amelia", "Arthur", "Bethany", "Bryan", "Charlotte", "Christine", "Christopher", "Danielle", "David", "Eleanor", "Francis", "George", "Isabel", "Jack", "Jane", "Jennie", "Jennifer", "Mark", "Melody", "Michael", "Nicholas", "Rose", "Sarah", "Sasha", "Simon", "Susan", "Sydney", "Toni", "Ursula", "William"],
"FUTURE":["Dreaded", "Expected", "Needed", "Desired", "Flew Towards", "Ran Towards", "Wanted", "Lusted for", "Yearned For", "Killed For", "Prayed For", "Cursed", "Accepted", "Hated", "Spurned", "Obeyed"],
"IMPERATIVE":["Must", "Should", "Shouldn't", "Mustn't", "Can", "Can't"],
"LASTNAME":["Bailey", "Black", "Brown", "Davies", "Green", "Jones", "Lane", "Smith", "White"],
"MODIFIER":["Acoustic", "Ambient", "Baroque", "Computer", "Constrained", "Electronic", "Esoteric", "Experimental", "Free", "Indie", "Low-Fi", "Minimal", "Modern", "Modernist", "Mumble", "Neoclassical", "New", "Orthodox", "Progressive", "Retro", "Romantic", "Sparse", "Trad", "Unorthodox", "Weird"],
"NOUN":["Acid", "Actor", "Actress", "Android", "Angel", "Ape", "Arcade", "Ash", "Asteroid", "Astronaut", "Atom", "Autumn", "Beach", "Blonde", "Blood", "Body", "Bone", "Book", "Box", "Brain", "Butterfly", "Castle", "Cave", "Chamber", "Chaos", "Chemical", "Children", "Church", "Claw", "Cloud", "Cocaine", "Coffin", "Cold", "Colour", "Computer", "Concrete", "Cosmic", "Crisis", "Crow", "Crystal", "Curse", "Dagger", "Day", "Death", "Demon", "Dilemma", "Doll", "Dream", "Drug", "Drum", "Dust", "Earring", "Eagle", "Earth", "East", "Egg", "Elephant", "Emperor", "Energy", "Factory", "Falcon", "Fashion", "Fear", "Field", "Fire", "Fish", "Flag", "Flame", "Fog", "Folly", "Gallows", "Gang", "Generator", "Ghost", "Glass", "Gold", "Granite", "Grave", "Guitar", "Gun", "Hammer", "Hand", "Hate", "Head", "Heat", "Heart", "Heartbreak", "Heaven", "Hell", "Highway", "Hot", "House", "Ice", "Image", "Iron", "Joy", "King", "Knife", "Lair", "Lament", "Land", "Law", "Lead", "Leather", "Limb", "Lord", "Love", "Machine", "Machinery", "Magic", "Man", "Marble", "Mercy", "Mind", "Mist", "Moon", "Nail", "Nation", "Neon", "Nerve", "Night", "Nightmare", "Noise", "North", "Oak", "Order", "Paper", "Pentagram", "Pet", "Piano", "Planet", "Plant", "Poison", "Porcelain", "Pride", "Priest", "Priestess", "Program", "Quest", "Radio", "Rain", "Redemption", "Revolution", "Rider", "Riot", "River", "Road", "Robot", "Rock", "Rocket", "Rose", "Rust", "Sabbath", "Scar", "Sculpture", "Sea", "Sex", "Shadow", "Silver", "Skull", "Smoke", "Snake", "Snow", "Song", "Soul", "South", "Space", "Spell", "Spike", "Star", "Steel", "Stone", "Storm", "Street", "Sulphur", "Sun", "Sword", "Teeth", "Temple", "Theatre", "Theory", "Thorn", "Thunder", "Tiger", "Time", "Transmission", "Tree", "Underground", "Unicorn", "Vicar", "Vixen", "Voodoo", "War", "Wasp", "Weed", "Werewolf", "West", "Wheel", "Wind", "Winter", "Witch", "Wizard", "Wolf", "Woman", "Word", "X-Ray", "Youth", "Zero"],
"PASTPERFECTVERB":["Flown to", "Seen", "Heard of", "Been to", "Arrived in", "Departed From", "Gone to", "Come to", "Exploded", "Come From"],
"PASTVERB":["Arrived In", "Believed", "Burned", "Departed", "Destroyed", "Exploded", "Finished", "Flew from", "Flew too", "Hated", "Have Harmed", "Heard", "Held", "Kissed", "Loved", "Mourned", "Passed", "Started", "Stole", "Touched"],
"PLACE":["Bangkok", "Barcelona", "Bay", "Beijing", "Berlin", "Cairo", "Castle", "Cemetery", "Earth", "Field", "Forest", "Hamburg", "Helsinki", "Island", "L.A.", "Lake", "Liverpool", "London", "Manchester", "Mars", "Meadow", "Miami", "Moscow", "New York", "Paris", "Pyramids", "Reykjavik", "River", "Rome", "Saigon", "Seattle", "Soho", "Stonehenge", "Swamp", "Tokyo", "Venus", "Warsaw"],
"PLURALS":["Apes", "Asteroids", "Birds", "Bones", "Cars", "Claws", "Colours", "Cries", "Crypts", "Crystals", "Dogs", "Dreams", "Drugs", "Eagles", "Emperors", "Explosions", "Faces", "Fields", "Fingers", "Fires", "Flags", "Flames", "Flowers", "Fruits", "Ghosts", "Giants", "Guns", "Hands", "Hills", "Insects", "Kings", "Knives", "Lies", "Limbs", "Machineries", "Machines", "Magicians", "Masks", "Masters", "Meteors", "Minds", "Monkeys", "Moons", "Mortals", "Mountains", "Orbits", "Organisms", "Particles", "Phantoms", "Pistols", "Pixels", "Popes", "Princes", "Princesses", "Pylons", "Queens", "Questions", "Rivers", "Roads", "Rockets", "Roses", "Scars", "Seas", "Shadows", "Shapes", "Signs", "Skulls", "Snakes", "Snows", "Spiders", "Stars", "Sultans", "Swamps", "Things", "Tombs", "Trees", "Umbrellas", "Vibrations", "Whales", "Wheels", "Whispers", "Winds", "Zombies"],
"POSSESSIVES":["Abdul's", "Abigail's", "Angela's", "Bernard's", "Christine's", "Daniel's", "Edgar's", "Emmanuel's", "Gabriel's", "Guinevere's", "Harry's ", "Jessica's", "John's", "Lucifer's", "Marian's", "Matilda's", "Merlin's", "Michael's", "Napoleon's", "Oscar's", "Romeo's", "Sebastian's", "Sophie's", "The Admiral's", "The Angel's", "The Devil's", "The Emperor's", "The Empress's", "The Farmhand's", "The Ghost's", "The Hangman's", "The Killer's", "The Lady's", "The Lord's", "The Master's", "The Mistress's", "The Priest's", "The Queen's", "Ursula's"],
"PRESENTVERB":["Agrees", "Arrives", "Brings", "Comes", "Cries", "Departs", "Dies", "Explodes", "Fights", "Flees", "Flies", "Greets", "Holds", "Ignores", "Kisses", "Leaves", "Loves", "Mourns", "Runs", "Soars", "Steals", "Walks", "Weeps"],
"PRONOUN":["He", "She", "It", "They", "We", "You"],
"PRONOUN2":["Him", "Her", "Them", "Us", "You"],
"PRONOUN3":["His", "Her", "Their", "Our", "Your", "My"],
"PRONOUNISARE":["He Is", "She Is", "It Is", "They Are", "We Are", "You Are", "We Are Not", "She Isn't", "He Isn't"],
"PRONOUNPAST":["They Have", "She Has", "He Has", "She Had", "He Had", "They Had", "They Hadn't", "She Hadn't", "He Hadn't"],
"SONGTYPE":["Anthem", "Aria", "Blues", "Cantata", "Chanson", "Dirge", "Elegy", "Hymn", "Lament", "Madrigal", "Motif", "Song", "Theme", "Tune", "Fugue"],
"SUBTYPE":["Acid", "Afro", "Art", "Bedroom", "Bubblegum", "Cassette", "Celtic", "Cowboy", "Dark", "Death", "Doom", "Drone", "Electro", "Freak", "Freestyle", "Future", "Ghetto", "Glitch", "Heavy", "Internet", "Jangle", "Latin", "Library", "Machine", "Minimal", "Occult", "Pagan", "Queer", "Retro", "Space", "Speed", "Surf", "Swamp", "Synth", "Techno", "Thrash", "Trip", "Viking", "Witch", "Wizard", "World"],
"TIME":["Afternoon", "the Age of Exploration", "Apocalypse", "Autumn", "Breakfast", "Century", "the Dark Ages", "Dawn", "Dinner", "Evening", "Friday", "Future", "the Gilded Age", "the Golden Age", "the Ice Age", "the Imperial Age", "Interbellum", "Lunch", "the Middle Ages", "Midnight", "Millenium", "Monday", "Moment", "Morning", "Night", "Noon", "Post Apocalypse", "Renaissance", "Saturday", "Spring", "the Stone Age", "Summer", "Sunday", "Sunrise", "Sunset", "Thursday", "Tuesday", "Twilight", "the Victorian Era", "Wednesday", "Weekend", "Winter"],
"VERB":["Advancing", "Arousing", "Awaiting", "Becoming", "Building", "Burning", "Calling", "Celebrating", "Crushing", "Disturbing", "Dreading", "Dying", "Enticing", "Expanding", "Exploring", "Fighting", "Flying", "Forgetting", "Glorifying", "Grieving", "Hammering", "Harvesting", "Holding", "Ignoring", "Jumping", "Justifying", "Kissing", "Leaving", "Living", "Looting", "Loving", "Lusting", "Mourning", "Numbering", "Numbing", "Observing", "Painting", "Passing", "Querying", "Remembering", "Romancing", "Running", "Sculpting", "Shocking", "Singing", "Smashing", "Spiralling", "Stalking", "Touching", "Understanding", "Visiting", "Walking"],
"VERBER":["Lover", "Eater", "Hunter", "Killer", "Stalker", "Singer"]
}